{
  "db_name": "PostgreSQL",
  "query": "SELECT song_id, COUNT(*) FROM song_likes WHERE song_id = ANY($1) GROUP BY song_id",
  "describe": {
    "columns": [
      {
        "ordinal": 0,
        "name": "song_id",
        "type_info": "Int8"
      },
      {
        "ordinal": 1,
        "name": "count",
        "type_info": "Int8"
      }
    ],
    "parameters": {
      "Left": [
        "Int8Array"
      ]
    },
    "nullable": [
      false,
      null
    ]
  },
  "hash": "6b63c2707be73b3577328afc08d80965d1eb8c4b680961e945dc9550133f45a9"
}
